gitpersona/__init__.py
gitpersona/analysis.py
gitpersona/cli.py
gitpersona/github_client.py
gitpersona-0.1.1.dist-info/licenses/LICENSE
gitpersona-0.1.1.dist-info/METADATA
gitpersona-0.1.1.dist-info/WHEEL
gitpersona-0.1.1.dist-info/entry_points.txt
gitpersona-0.1.1.dist-info/top_level.txt
gitpersona-0.1.1.dist-info/RECORD
