Metadata-Version: 2.4
Name: gitpersona
Version: 0.1.1
Summary: Developer persona and analytics toolkit for GitHub profiles
Author: rdarshan927
Requires-Python: >=3.8
License-File: LICENSE
Requires-Dist: requests
Dynamic: license-file
